patrol_graph/__init__.py
patrol_graph/__main__.py
patrol_graph/patrol_graph.py
patrol_graph-0.2.0.dist-info/METADATA
patrol_graph-0.2.0.dist-info/WHEEL
patrol_graph-0.2.0.dist-info/licenses/LICENSE.txt
patrol_graph-0.2.0.dist-info/RECORD
